CHANGES
LICENSE
MANIFEST.in
README
README.rst
requirements.txt
setup.py
gaeenv/__init__.py
gaeenv/main.py
gaeenv/requirements.py
gaeenv/sdk.py
gaeenv/utils.py
gaeenv/virtualenv.py
gaeenv.egg-info/PKG-INFO
gaeenv.egg-info/SOURCES.txt
gaeenv.egg-info/dependency_links.txt
gaeenv.egg-info/entry_points.txt
gaeenv.egg-info/not-zip-safe
gaeenv.egg-info/requires.txt
gaeenv.egg-info/top_level.txt