Metadata-Version: 1.1
Name: gaeenv
Version: 0.1.4
Summary: Goole App Engine Virtualenv tools
Home-page: https://github.com/llinder/gaeenv
Author: Lance Linder
Author-email: llinder@gmail.com
License: Apache 2.0
Platform: any
Classifier: Development Status :: 3 - Alpha
Classifier: Environment :: Web Environment
Classifier: Intended Audience :: Developers
Classifier: License :: OSI Approved :: Apache Software License
Classifier: Programming Language :: Python
Classifier: Topic :: Software Development :: Libraries :: Python Modules
